libyamlconf/__init__.py
libyamlconf/py.typed
libyamlconf/verify.py
libyamlconf/yaml.py
libyamlconf-1.2.2.dist-info/METADATA
libyamlconf-1.2.2.dist-info/WHEEL
libyamlconf-1.2.2.dist-info/licenses/LICENSE
libyamlconf-1.2.2.dist-info/RECORD
