Metadata-Version: 2.4
Name: libyamlconf
Version: 1.2.2
Summary: Load and verify hierarchical yaml config files.
Project-URL: Homepage, https://github.com/eLiSCHe/libyamlconf
Author-email: Thomas Irgang <thomas@irgang.eu>
License-File: LICENSE
Classifier: Development Status :: 3 - Alpha
Classifier: License :: OSI Approved :: GNU General Public License v3 (GPLv3)
Classifier: Programming Language :: Python :: 3
Requires-Python: >=3.10
Requires-Dist: deepdiff>=8.2.0
Requires-Dist: pydantic>=2.10.6
Requires-Dist: pyyaml>=6.0.2
